odoo10_addon_openeducat_fees-10.0.3.0.0.99.dev2-py2.7-nspkg.pth
odoo/addons/openeducat_fees/README.rst
odoo/addons/openeducat_fees/__init__.py
odoo/addons/openeducat_fees/__manifest__.py
odoo/addons/openeducat_fees/demo/course_demo.xml
odoo/addons/openeducat_fees/demo/fees_terms_demo.xml
odoo/addons/openeducat_fees/demo/fees_terms_line_demo.xml
odoo/addons/openeducat_fees/models/__init__.py
odoo/addons/openeducat_fees/models/course.py
odoo/addons/openeducat_fees/models/fees_terms.py
odoo/addons/openeducat_fees/models/student.py
odoo/addons/openeducat_fees/security/fees_security.xml
odoo/addons/openeducat_fees/security/ir.model.access.csv
odoo/addons/openeducat_fees/static/description/financial.png
odoo/addons/openeducat_fees/static/description/icon.png
odoo/addons/openeducat_fees/static/description/index.html
odoo/addons/openeducat_fees/static/description/openeducat_fees_banner.jpg
odoo/addons/openeducat_fees/static/description/openeducat_logo.png
odoo/addons/openeducat_fees/views/course_view.xml
odoo/addons/openeducat_fees/views/fees_terms_view.xml
odoo/addons/openeducat_fees/views/main_view.xml
odoo/addons/openeducat_fees/views/student_view.xml
odoo10_addon_openeducat_fees-10.0.3.0.0.99.dev2.dist-info/DESCRIPTION.rst
odoo10_addon_openeducat_fees-10.0.3.0.0.99.dev2.dist-info/METADATA
odoo10_addon_openeducat_fees-10.0.3.0.0.99.dev2.dist-info/RECORD
odoo10_addon_openeducat_fees-10.0.3.0.0.99.dev2.dist-info/WHEEL
odoo10_addon_openeducat_fees-10.0.3.0.0.99.dev2.dist-info/metadata.json
odoo10_addon_openeducat_fees-10.0.3.0.0.99.dev2.dist-info/namespace_packages.txt
odoo10_addon_openeducat_fees-10.0.3.0.0.99.dev2.dist-info/top_level.txt
